autoCase/__init__.py
autoCase/case/__init__.py
autoCase/case/caseConverter.py
autoCase/core/main.py
autoCase/core/validator.py
autoCase/wordSplitter/AiSplitter.py
autoCase/wordSplitter/CaseSplitter.py
autoCase/wordSplitter/DictSplitter.py
autoCase/wordSplitter/RegexSplitter.py
autoCase/wordSplitter/__init__.py
autoCase/wordSplitter/utils.py
autocase-0.0.4.dist-info/WHEEL
autocase-0.0.4.dist-info/METADATA
autocase-0.0.4.dist-info/RECORD
